diaspora/__init__.py
diaspora/__main__.py
diaspora/hooking/__init__.py
diaspora/hooking/ante_build_hook.py
diaspora/hooking/ante_release_hook.py
diaspora/hooking/post_build_hook.py
diaspora/hooking/post_release_hook.py
diaspora/pyrustic_data/hooking.json
diaspora/pyrustic_data/hubstore.json
diaspora/pyrustic_data/release_info.json
secret/SCRATCH.py
secret/__init__.py
tests/__init__.py
diaspora-0.0.2.dist-info/LICENSE
diaspora-0.0.2.dist-info/METADATA
diaspora-0.0.2.dist-info/WHEEL
diaspora-0.0.2.dist-info/entry_points.txt
diaspora-0.0.2.dist-info/top_level.txt
diaspora-0.0.2.dist-info/RECORD
