Metadata-Version: 2.1
Name: diaspora
Version: 0.0.2
Summary: Communicating between loosely coupled components
Home-page: https://github.com/pyrustic/diaspora
Author: Pyrustic Evangelist
Author-email: pyrustic@protonmail.com
Maintainer: Pyrustic Evangelist
Maintainer-email: pyrustic@protonmail.com
License: MIT
Keywords: library,event-notification,pub-sub,event-driven,communication,loosely-coupled
Platform: UNKNOWN
Classifier: Programming Language :: Python :: 3
Classifier: License :: OSI Approved :: MIT License
Classifier: Operating System :: OS Independent
Requires-Python: >=3.5
